mds/__init__.py
mds/conf/__init__.py
mds/conf/global_settings.py
mds/core/__init__.py
mds/core/copernicus.py
mds/core/mds_s3.py
mds/core/s3_singleton.py
mds/core/s3file.py
mds/core/utils.py
mds/core/wrapper.py
mds/mng/__init__.py
mds/mng/cli.py
mds/mng/initializer.py
mds/mng/s3_group.py
mds/mng/wrapper_group.py
mds/utils/__init__.py
mds/utils/log.py
mds/utils/module_loading.py
mds/utils/str_parser.py
mds_toolbox-2.1.dist-info/LICENSE.txt
mds_toolbox-2.1.dist-info/METADATA
mds_toolbox-2.1.dist-info/WHEEL
mds_toolbox-2.1.dist-info/entry_points.txt
mds_toolbox-2.1.dist-info/RECORD
