Metadata-Version: 2.1
Name: mds-toolbox
Version: 2.1
Summary: A custom CMCC library to list and download data from the Marine Data Store
Keywords: copernicus,copernicusmarine,mds,marine data store
Author: Antonio Mariani
Author-email: antonio.mariani@cmcc.it
Requires-Python: >=3.9,<3.13
Classifier: Programming Language :: Python :: 3
Classifier: Programming Language :: Python :: 3.9
Classifier: Programming Language :: Python :: 3.10
Classifier: Programming Language :: Python :: 3.11
Classifier: Programming Language :: Python :: 3.12
Requires-Dist: boto3 (>=1.37.4,<2.0.0)
Requires-Dist: click (>=8.1.8,<9.0.0)
Requires-Dist: copernicusmarine (>=2.2.2)
Requires-Dist: zarr (>=2.13.3)
